graspfile/__init__.py
graspfile/cut.py
graspfile/grid.py
graspfile/numpy_utilities.py
graspfile/torfile.py
graspfile/torparser.py
graspfile/analysis/__init__.py
graspfile/analysis/grid.py
graspfile/analysis/reflectance.py
graspfile/plot/__init__.py
python_graspfile-0.4.1.dist-info/AUTHORS.rst
python_graspfile-0.4.1.dist-info/LICENSE
python_graspfile-0.4.1.dist-info/METADATA
python_graspfile-0.4.1.dist-info/WHEEL
python_graspfile-0.4.1.dist-info/entry_points.txt
python_graspfile-0.4.1.dist-info/top_level.txt
python_graspfile-0.4.1.dist-info/RECORD
