Metadata-Version: 2.1
Name: python-graspfile
Version: 0.4.1
Summary: A package for reading, manipulating and eventually writing files output from TICRA Tools GRASP and CHAMP software using numpy etc.
Home-page: https://github.com/PaulKGrimes/python-graspfile
Author: Paul Grimes
Author-email: pgrimes@cfa.harvard.edu
License: MIT
Project-URL: Documentation, https://python-graspfile.readthedocs.io/
Project-URL: Changelog, https://python-graspfile.readthedocs.io/en/latest/changelog.html
Project-URL: Issue Tracker, https://github.com/PaulKGrimes/python-graspfile/issues
Platform: UNKNOWN
Classifier: Development Status :: 4 - Beta
Classifier: Intended Audience :: Science/Research
Classifier: License :: OSI Approved :: MIT License
Classifier: Operating System :: Unix
Classifier: Operating System :: POSIX
Classifier: Operating System :: Microsoft :: Windows
Classifier: Programming Language :: Python
Classifier: Programming Language :: Python :: 2.7
Classifier: Programming Language :: Python :: 3
Classifier: Programming Language :: Python :: 3.5
Classifier: Programming Language :: Python :: 3.6
Classifier: Programming Language :: Python :: 3.7
Classifier: Programming Language :: Python :: 3.8
Classifier: Topic :: Utilities
Requires-Python: >=2.7, !=3.0.*, !=3.1.*, !=3.2.*, !=3.3.*, !=3.4.*
License-File: LICENSE
License-File: AUTHORS.rst
Requires-Dist: matplotlib
Requires-Dist: numpy
Requires-Dist: sphinx-automodapi
Requires-Dist: pyparsing
Requires-Dist: pytest
